[
  {
    "id": 1141294247,
    "node_id": "R_kgDORAbEpw",
    "name": "cheesits456",
    "full_name": "mostafanagedy/cheesits456",
    "private": false,
    "owner": {
      "login": "mostafanagedy",
      "id": 214047181,
      "node_id": "U_kgDODMIZzQ",
      "avatar_url": "https://avatars.githubusercontent.com/u/214047181?v=4",
      "gravatar_id": "",
      "url": "https://api.github.com/users/mostafanagedy",
      "html_url": "https://github.com/mostafanagedy",
      "followers_url": "https://api.github.com/users/mostafanagedy/followers",
      "following_url": "https://api.github.com/users/mostafanagedy/following{/other_user}",
      "gists_url": "https://api.github.com/users/mostafanagedy/gists{/gist_id}",
      "starred_url": "https://api.github.com/users/mostafanagedy/starred{/owner}{/repo}",
      "subscriptions_url": "https://api.github.com/users/mostafanagedy/subscriptions",
      "organizations_url": "https://api.github.com/users/mostafanagedy/orgs",
      "repos_url": "https://api.github.com/users/mostafanagedy/repos",
      "events_url": "https://api.github.com/users/mostafanagedy/events{/privacy}",
      "received_events_url": "https://api.github.com/users/mostafanagedy/received_events",
      "type": "User",
      "user_view_type": "public",
      "site_admin": false
    },
    "html_url": "https://github.com/mostafanagedy/cheesits456",
    "description": null,
    "fork": true,
    "url": "https://api.github.com/repos/mostafanagedy/cheesits456",
    "forks_url": "https://api.github.com/repos/mostafanagedy/cheesits456/forks",
    "keys_url": "https://api.github.com/repos/mostafanagedy/cheesits456/keys{/key_id}",
    "collaborators_url": "https://api.github.com/repos/mostafanagedy/cheesits456/collaborators{/collaborator}",
    "teams_url": "https://api.github.com/repos/mostafanagedy/cheesits456/teams",
    "hooks_url": "https://api.github.com/repos/mostafanagedy/cheesits456/hooks",
    "issue_events_url": "https://api.github.com/repos/mostafanagedy/cheesits456/issues/events{/number}",
    "events_url": "https://api.github.com/repos/mostafanagedy/cheesits456/events",
    "assignees_url": "https://api.github.com/repos/mostafanagedy/cheesits456/assignees{/user}",
    "branches_url": "https://api.github.com/repos/mostafanagedy/cheesits456/branches{/branch}",
    "tags_url": "https://api.github.com/repos/mostafanagedy/cheesits456/tags",
    "blobs_url": "https://api.github.com/repos/mostafanagedy/cheesits456/git/blobs{/sha}",
    "git_tags_url": "https://api.github.com/repos/mostafanagedy/cheesits456/git/tags{/sha}",
    "git_refs_url": "https://api.github.com/repos/mostafanagedy/cheesits456/git/refs{/sha}",
    "trees_url": "https://api.github.com/repos/mostafanagedy/cheesits456/git/trees{/sha}",
    "statuses_url": "https://api.github.com/repos/mostafanagedy/cheesits456/statuses/{sha}",
    "languages_url": "https://api.github.com/repos/mostafanagedy/cheesits456/languages",
    "stargazers_url": "https://api.github.com/repos/mostafanagedy/cheesits456/stargazers",
    "contributors_url": "https://api.github.com/repos/mostafanagedy/cheesits456/contributors",
    "subscribers_url": "https://api.github.com/repos/mostafanagedy/cheesits456/subscribers",
    "subscription_url": "https://api.github.com/repos/mostafanagedy/cheesits456/subscription",
    "commits_url": "https://api.github.com/repos/mostafanagedy/cheesits456/commits{/sha}",
    "git_commits_url": "https://api.github.com/repos/mostafanagedy/cheesits456/git/commits{/sha}",
    "comments_url": "https://api.github.com/repos/mostafanagedy/cheesits456/comments{/number}",
    "issue_comment_url": "https://api.github.com/repos/mostafanagedy/cheesits456/issues/comments{/number}",
    "contents_url": "https://api.github.com/repos/mostafanagedy/cheesits456/contents/{+path}",
    "compare_url": "https://api.github.com/repos/mostafanagedy/cheesits456/compare/{base}...{head}",
    "merges_url": "https://api.github.com/repos/mostafanagedy/cheesits456/merges",
    "archive_url": "https://api.github.com/repos/mostafanagedy/cheesits456/{archive_format}{/ref}",
    "downloads_url": "https://api.github.com/repos/mostafanagedy/cheesits456/downloads",
    "issues_url": "https://api.github.com/repos/mostafanagedy/cheesits456/issues{/number}",
    "pulls_url": "https://api.github.com/repos/mostafanagedy/cheesits456/pulls{/number}",
    "milestones_url": "https://api.github.com/repos/mostafanagedy/cheesits456/milestones{/number}",
    "notifications_url": "https://api.github.com/repos/mostafanagedy/cheesits456/notifications{?since,all,participating}",
    "labels_url": "https://api.github.com/repos/mostafanagedy/cheesits456/labels{/name}",
    "releases_url": "https://api.github.com/repos/mostafanagedy/cheesits456/releases{/id}",
    "deployments_url": "https://api.github.com/repos/mostafanagedy/cheesits456/deployments",
    "created_at": "2026-01-24T15:56:22Z",
    "updated_at": "2026-01-24T15:56:22Z",
    "pushed_at": "2025-12-29T21:24:17Z",
    "git_url": "git://github.com/mostafanagedy/cheesits456.git",
    "ssh_url": "git@github.com:mostafanagedy/cheesits456.git",
    "clone_url": "https://github.com/mostafanagedy/cheesits456.git",
    "svn_url": "https://github.com/mostafanagedy/cheesits456",
    "homepage": "",
    "size": 34979,
    "stargazers_count": 0,
    "watchers_count": 0,
    "language": null,
    "has_issues": false,
    "has_projects": true,
    "has_downloads": true,
    "has_wiki": false,
    "has_pages": false,
    "has_discussions": false,
    "forks_count": 0,
    "mirror_url": null,
    "archived": false,
    "disabled": false,
    "open_issues_count": 0,
    "license": null,
    "allow_forking": true,
    "is_template": false,
    "web_commit_signoff_required": false,
    "has_pull_requests": true,
    "pull_request_creation_policy": "all",
    "topics": [

    ],
    "visibility": "public",
    "forks": 0,
    "open_issues": 0,
    "watchers": 0,
    "default_branch": "master"
  },
  {
    "id": 1163297386,
    "node_id": "R_kgDORVaCag",
    "name": "html-css-and-javascript-building-the-web-4479542",
    "full_name": "mostafanagedy/html-css-and-javascript-building-the-web-4479542",
    "private": false,
    "owner": {
      "login": "mostafanagedy",
      "id": 214047181,
      "node_id": "U_kgDODMIZzQ",
      "avatar_url": "https://avatars.githubusercontent.com/u/214047181?v=4",
      "gravatar_id": "",
      "url": "https://api.github.com/users/mostafanagedy",
      "html_url": "https://github.com/mostafanagedy",
      "followers_url": "https://api.github.com/users/mostafanagedy/followers",
      "following_url": "https://api.github.com/users/mostafanagedy/following{/other_user}",
      "gists_url": "https://api.github.com/users/mostafanagedy/gists{/gist_id}",
      "starred_url": "https://api.github.com/users/mostafanagedy/starred{/owner}{/repo}",
      "subscriptions_url": "https://api.github.com/users/mostafanagedy/subscriptions",
      "organizations_url": "https://api.github.com/users/mostafanagedy/orgs",
      "repos_url": "https://api.github.com/users/mostafanagedy/repos",
      "events_url": "https://api.github.com/users/mostafanagedy/events{/privacy}",
      "received_events_url": "https://api.github.com/users/mostafanagedy/received_events",
      "type": "User",
      "user_view_type": "public",
      "site_admin": false
    },
    "html_url": "https://github.com/mostafanagedy/html-css-and-javascript-building-the-web-4479542",
    "description": "This is a repository for the LinkedIn Learning course HTML, CSS, and JavaScript: Building the Web",
    "fork": true,
    "url": "https://api.github.com/repos/mostafanagedy/html-css-and-javascript-building-the-web-4479542",
    "forks_url": "https://api.github.com/repos/mostafanagedy/html-css-and-javascript-building-the-web-4479542/forks",
    "keys_url": "https://api.github.com/repos/mostafanagedy/html-css-and-javascript-building-the-web-4479542/keys{/key_id}",
    "collaborators_url": "https://api.github.com/repos/mostafanagedy/html-css-and-javascript-building-the-web-4479542/collaborators{/collaborator}",
    "teams_url": "https://api.github.com/repos/mostafanagedy/html-css-and-javascript-building-the-web-4479542/teams",
    "hooks_url": "https://api.github.com/repos/mostafanagedy/html-css-and-javascript-building-the-web-4479542/hooks",
    "issue_events_url": "https://api.github.com/repos/mostafanagedy/html-css-and-javascript-building-the-web-4479542/issues/events{/number}",
    "events_url": "https://api.github.com/repos/mostafanagedy/html-css-and-javascript-building-the-web-4479542/events",
    "assignees_url": "https://api.github.com/repos/mostafanagedy/html-css-and-javascript-building-the-web-4479542/assignees{/user}",
    "branches_url": "https://api.github.com/repos/mostafanagedy/html-css-and-javascript-building-the-web-4479542/branches{/branch}",
    "tags_url": "https://api.github.com/repos/mostafanagedy/html-css-and-javascript-building-the-web-4479542/tags",
    "blobs_url": "https://api.github.com/repos/mostafanagedy/html-css-and-javascript-building-the-web-4479542/git/blobs{/sha}",
    "git_tags_url": "https://api.github.com/repos/mostafanagedy/html-css-and-javascript-building-the-web-4479542/git/tags{/sha}",
    "git_refs_url": "https://api.github.com/repos/mostafanagedy/html-css-and-javascript-building-the-web-4479542/git/refs{/sha}",
    "trees_url": "https://api.github.com/repos/mostafanagedy/html-css-and-javascript-building-the-web-4479542/git/trees{/sha}",
    "statuses_url": "https://api.github.com/repos/mostafanagedy/html-css-and-javascript-building-the-web-4479542/statuses/{sha}",
    "languages_url": "https://api.github.com/repos/mostafanagedy/html-css-and-javascript-building-the-web-4479542/languages",
    "stargazers_url": "https://api.github.com/repos/mostafanagedy/html-css-and-javascript-building-the-web-4479542/stargazers",
    "contributors_url": "https://api.github.com/repos/mostafanagedy/html-css-and-javascript-building-the-web-4479542/contributors",
    "subscribers_url": "https://api.github.com/repos/mostafanagedy/html-css-and-javascript-building-the-web-4479542/subscribers",
    "subscription_url": "https://api.github.com/repos/mostafanagedy/html-css-and-javascript-building-the-web-4479542/subscription",
    "commits_url": "https://api.github.com/repos/mostafanagedy/html-css-and-javascript-building-the-web-4479542/commits{/sha}",
    "git_commits_url": "https://api.github.com/repos/mostafanagedy/html-css-and-javascript-building-the-web-4479542/git/commits{/sha}",
    "comments_url": "https://api.github.com/repos/mostafanagedy/html-css-and-javascript-building-the-web-4479542/comments{/number}",
    "issue_comment_url": "https://api.github.com/repos/mostafanagedy/html-css-and-javascript-building-the-web-4479542/issues/comments{/number}",
    "contents_url": "https://api.github.com/repos/mostafanagedy/html-css-and-javascript-building-the-web-4479542/contents/{+path}",
    "compare_url": "https://api.github.com/repos/mostafanagedy/html-css-and-javascript-building-the-web-4479542/compare/{base}...{head}",
    "merges_url": "https://api.github.com/repos/mostafanagedy/html-css-and-javascript-building-the-web-4479542/merges",
    "archive_url": "https://api.github.com/repos/mostafanagedy/html-css-and-javascript-building-the-web-4479542/{archive_format}{/ref}",
    "downloads_url": "https://api.github.com/repos/mostafanagedy/html-css-and-javascript-building-the-web-4479542/downloads",
    "issues_url": "https://api.github.com/repos/mostafanagedy/html-css-and-javascript-building-the-web-4479542/issues{/number}",
    "pulls_url": "https://api.github.com/repos/mostafanagedy/html-css-and-javascript-building-the-web-4479542/pulls{/number}",
    "milestones_url": "https://api.github.com/repos/mostafanagedy/html-css-and-javascript-building-the-web-4479542/milestones{/number}",
    "notifications_url": "https://api.github.com/repos/mostafanagedy/html-css-and-javascript-building-the-web-4479542/notifications{?since,all,participating}",
    "labels_url": "https://api.github.com/repos/mostafanagedy/html-css-and-javascript-building-the-web-4479542/labels{/name}",
    "releases_url": "https://api.github.com/repos/mostafanagedy/html-css-and-javascript-building-the-web-4479542/releases{/id}",
    "deployments_url": "https://api.github.com/repos/mostafanagedy/html-css-and-javascript-building-the-web-4479542/deployments",
    "created_at": "2026-02-21T12:10:19Z",
    "updated_at": "2026-02-21T12:10:20Z",
    "pushed_at": "2025-09-02T17:53:23Z",
    "git_url": "git://github.com/mostafanagedy/html-css-and-javascript-building-the-web-4479542.git",
    "ssh_url": "git@github.com:mostafanagedy/html-css-and-javascript-building-the-web-4479542.git",
    "clone_url": "https://github.com/mostafanagedy/html-css-and-javascript-building-the-web-4479542.git",
    "svn_url": "https://github.com/mostafanagedy/html-css-and-javascript-building-the-web-4479542",
    "homepage": null,
    "size": 4714,
    "stargazers_count": 0,
    "watchers_count": 0,
    "language": null,
    "has_issues": false,
    "has_projects": true,
    "has_downloads": true,
    "has_wiki": true,
    "has_pages": false,
    "has_discussions": false,
    "forks_count": 0,
    "mirror_url": null,
    "archived": false,
    "disabled": false,
    "open_issues_count": 0,
    "license": {
      "key": "other",
      "name": "Other",
      "spdx_id": "NOASSERTION",
      "url": null,
      "node_id": "MDc6TGljZW5zZTA="
    },
    "allow_forking": true,
    "is_template": false,
    "web_commit_signoff_required": false,
    "has_pull_requests": true,
    "pull_request_creation_policy": "all",
    "topics": [

    ],
    "visibility": "public",
    "forks": 0,
    "open_issues": 0,
    "watchers": 0,
    "default_branch": "main"
  },
  {
    "id": 1168582147,
    "node_id": "R_kgDORacmAw",
    "name": "it-s-my",
    "full_name": "mostafanagedy/it-s-my",
    "private": false,
    "owner": {
      "login": "mostafanagedy",
      "id": 214047181,
      "node_id": "U_kgDODMIZzQ",
      "avatar_url": "https://avatars.githubusercontent.com/u/214047181?v=4",
      "gravatar_id": "",
      "url": "https://api.github.com/users/mostafanagedy",
      "html_url": "https://github.com/mostafanagedy",
      "followers_url": "https://api.github.com/users/mostafanagedy/followers",
      "following_url": "https://api.github.com/users/mostafanagedy/following{/other_user}",
      "gists_url": "https://api.github.com/users/mostafanagedy/gists{/gist_id}",
      "starred_url": "https://api.github.com/users/mostafanagedy/starred{/owner}{/repo}",
      "subscriptions_url": "https://api.github.com/users/mostafanagedy/subscriptions",
      "organizations_url": "https://api.github.com/users/mostafanagedy/orgs",
      "repos_url": "https://api.github.com/users/mostafanagedy/repos",
      "events_url": "https://api.github.com/users/mostafanagedy/events{/privacy}",
      "received_events_url": "https://api.github.com/users/mostafanagedy/received_events",
      "type": "User",
      "user_view_type": "public",
      "site_admin": false
    },
    "html_url": "https://github.com/mostafanagedy/it-s-my",
    "description": null,
    "fork": false,
    "url": "https://api.github.com/repos/mostafanagedy/it-s-my",
    "forks_url": "https://api.github.com/repos/mostafanagedy/it-s-my/forks",
    "keys_url": "https://api.github.com/repos/mostafanagedy/it-s-my/keys{/key_id}",
    "collaborators_url": "https://api.github.com/repos/mostafanagedy/it-s-my/collaborators{/collaborator}",
    "teams_url": "https://api.github.com/repos/mostafanagedy/it-s-my/teams",
    "hooks_url": "https://api.github.com/repos/mostafanagedy/it-s-my/hooks",
    "issue_events_url": "https://api.github.com/repos/mostafanagedy/it-s-my/issues/events{/number}",
    "events_url": "https://api.github.com/repos/mostafanagedy/it-s-my/events",
    "assignees_url": "https://api.github.com/repos/mostafanagedy/it-s-my/assignees{/user}",
    "branches_url": "https://api.github.com/repos/mostafanagedy/it-s-my/branches{/branch}",
    "tags_url": "https://api.github.com/repos/mostafanagedy/it-s-my/tags",
    "blobs_url": "https://api.github.com/repos/mostafanagedy/it-s-my/git/blobs{/sha}",
    "git_tags_url": "https://api.github.com/repos/mostafanagedy/it-s-my/git/tags{/sha}",
    "git_refs_url": "https://api.github.com/repos/mostafanagedy/it-s-my/git/refs{/sha}",
    "trees_url": "https://api.github.com/repos/mostafanagedy/it-s-my/git/trees{/sha}",
    "statuses_url": "https://api.github.com/repos/mostafanagedy/it-s-my/statuses/{sha}",
    "languages_url": "https://api.github.com/repos/mostafanagedy/it-s-my/languages",
    "stargazers_url": "https://api.github.com/repos/mostafanagedy/it-s-my/stargazers",
    "contributors_url": "https://api.github.com/repos/mostafanagedy/it-s-my/contributors",
    "subscribers_url": "https://api.github.com/repos/mostafanagedy/it-s-my/subscribers",
    "subscription_url": "https://api.github.com/repos/mostafanagedy/it-s-my/subscription",
    "commits_url": "https://api.github.com/repos/mostafanagedy/it-s-my/commits{/sha}",
    "git_commits_url": "https://api.github.com/repos/mostafanagedy/it-s-my/git/commits{/sha}",
    "comments_url": "https://api.github.com/repos/mostafanagedy/it-s-my/comments{/number}",
    "issue_comment_url": "https://api.github.com/repos/mostafanagedy/it-s-my/issues/comments{/number}",
    "contents_url": "https://api.github.com/repos/mostafanagedy/it-s-my/contents/{+path}",
    "compare_url": "https://api.github.com/repos/mostafanagedy/it-s-my/compare/{base}...{head}",
    "merges_url": "https://api.github.com/repos/mostafanagedy/it-s-my/merges",
    "archive_url": "https://api.github.com/repos/mostafanagedy/it-s-my/{archive_format}{/ref}",
    "downloads_url": "https://api.github.com/repos/mostafanagedy/it-s-my/downloads",
    "issues_url": "https://api.github.com/repos/mostafanagedy/it-s-my/issues{/number}",
    "pulls_url": "https://api.github.com/repos/mostafanagedy/it-s-my/pulls{/number}",
    "milestones_url": "https://api.github.com/repos/mostafanagedy/it-s-my/milestones{/number}",
    "notifications_url": "https://api.github.com/repos/mostafanagedy/it-s-my/notifications{?since,all,participating}",
    "labels_url": "https://api.github.com/repos/mostafanagedy/it-s-my/labels{/name}",
    "releases_url": "https://api.github.com/repos/mostafanagedy/it-s-my/releases{/id}",
    "deployments_url": "https://api.github.com/repos/mostafanagedy/it-s-my/deployments",
    "created_at": "2026-02-27T15:01:02Z",
    "updated_at": "2026-02-27T15:14:24Z",
    "pushed_at": "2026-02-27T15:13:38Z",
    "git_url": "git://github.com/mostafanagedy/it-s-my.git",
    "ssh_url": "git@github.com:mostafanagedy/it-s-my.git",
    "clone_url": "https://github.com/mostafanagedy/it-s-my.git",
    "svn_url": "https://github.com/mostafanagedy/it-s-my",
    "homepage": "https://it-s-my.vercel.app",
    "size": 38,
    "stargazers_count": 0,
    "watchers_count": 0,
    "language": "TypeScript",
    "has_issues": true,
    "has_projects": true,
    "has_downloads": true,
    "has_wiki": true,
    "has_pages": false,
    "has_discussions": false,
    "forks_count": 0,
    "mirror_url": null,
    "archived": false,
    "disabled": false,
    "open_issues_count": 0,
    "license": null,
    "allow_forking": true,
    "is_template": false,
    "web_commit_signoff_required": false,
    "has_pull_requests": true,
    "pull_request_creation_policy": "all",
    "topics": [

    ],
    "visibility": "public",
    "forks": 0,
    "open_issues": 0,
    "watchers": 0,
    "default_branch": "main"
  },
  {
    "id": 1141288911,
    "node_id": "R_kgDORAavzw",
    "name": "MostafaNagdy",
    "full_name": "mostafanagedy/MostafaNagdy",
    "private": false,
    "owner": {
      "login": "mostafanagedy",
      "id": 214047181,
      "node_id": "U_kgDODMIZzQ",
      "avatar_url": "https://avatars.githubusercontent.com/u/214047181?v=4",
      "gravatar_id": "",
      "url": "https://api.github.com/users/mostafanagedy",
      "html_url": "https://github.com/mostafanagedy",
      "followers_url": "https://api.github.com/users/mostafanagedy/followers",
      "following_url": "https://api.github.com/users/mostafanagedy/following{/other_user}",
      "gists_url": "https://api.github.com/users/mostafanagedy/gists{/gist_id}",
      "starred_url": "https://api.github.com/users/mostafanagedy/starred{/owner}{/repo}",
      "subscriptions_url": "https://api.github.com/users/mostafanagedy/subscriptions",
      "organizations_url": "https://api.github.com/users/mostafanagedy/orgs",
      "repos_url": "https://api.github.com/users/mostafanagedy/repos",
      "events_url": "https://api.github.com/users/mostafanagedy/events{/privacy}",
      "received_events_url": "https://api.github.com/users/mostafanagedy/received_events",
      "type": "User",
      "user_view_type": "public",
      "site_admin": false
    },
    "html_url": "https://github.com/mostafanagedy/MostafaNagdy",
    "description": null,
    "fork": false,
    "url": "https://api.github.com/repos/mostafanagedy/MostafaNagdy",
    "forks_url": "https://api.github.com/repos/mostafanagedy/MostafaNagdy/forks",
    "keys_url": "https://api.github.com/repos/mostafanagedy/MostafaNagdy/keys{/key_id}",
    "collaborators_url": "https://api.github.com/repos/mostafanagedy/MostafaNagdy/collaborators{/collaborator}",
    "teams_url": "https://api.github.com/repos/mostafanagedy/MostafaNagdy/teams",
    "hooks_url": "https://api.github.com/repos/mostafanagedy/MostafaNagdy/hooks",
    "issue_events_url": "https://api.github.com/repos/mostafanagedy/MostafaNagdy/issues/events{/number}",
    "events_url": "https://api.github.com/repos/mostafanagedy/MostafaNagdy/events",
    "assignees_url": "https://api.github.com/repos/mostafanagedy/MostafaNagdy/assignees{/user}",
    "branches_url": "https://api.github.com/repos/mostafanagedy/MostafaNagdy/branches{/branch}",
    "tags_url": "https://api.github.com/repos/mostafanagedy/MostafaNagdy/tags",
    "blobs_url": "https://api.github.com/repos/mostafanagedy/MostafaNagdy/git/blobs{/sha}",
    "git_tags_url": "https://api.github.com/repos/mostafanagedy/MostafaNagdy/git/tags{/sha}",
    "git_refs_url": "https://api.github.com/repos/mostafanagedy/MostafaNagdy/git/refs{/sha}",
    "trees_url": "https://api.github.com/repos/mostafanagedy/MostafaNagdy/git/trees{/sha}",
    "statuses_url": "https://api.github.com/repos/mostafanagedy/MostafaNagdy/statuses/{sha}",
    "languages_url": "https://api.github.com/repos/mostafanagedy/MostafaNagdy/languages",
    "stargazers_url": "https://api.github.com/repos/mostafanagedy/MostafaNagdy/stargazers",
    "contributors_url": "https://api.github.com/repos/mostafanagedy/MostafaNagdy/contributors",
    "subscribers_url": "https://api.github.com/repos/mostafanagedy/MostafaNagdy/subscribers",
    "subscription_url": "https://api.github.com/repos/mostafanagedy/MostafaNagdy/subscription",
    "commits_url": "https://api.github.com/repos/mostafanagedy/MostafaNagdy/commits{/sha}",
    "git_commits_url": "https://api.github.com/repos/mostafanagedy/MostafaNagdy/git/commits{/sha}",
    "comments_url": "https://api.github.com/repos/mostafanagedy/MostafaNagdy/comments{/number}",
    "issue_comment_url": "https://api.github.com/repos/mostafanagedy/MostafaNagdy/issues/comments{/number}",
    "contents_url": "https://api.github.com/repos/mostafanagedy/MostafaNagdy/contents/{+path}",
    "compare_url": "https://api.github.com/repos/mostafanagedy/MostafaNagdy/compare/{base}...{head}",
    "merges_url": "https://api.github.com/repos/mostafanagedy/MostafaNagdy/merges",
    "archive_url": "https://api.github.com/repos/mostafanagedy/MostafaNagdy/{archive_format}{/ref}",
    "downloads_url": "https://api.github.com/repos/mostafanagedy/MostafaNagdy/downloads",
    "issues_url": "https://api.github.com/repos/mostafanagedy/MostafaNagdy/issues{/number}",
    "pulls_url": "https://api.github.com/repos/mostafanagedy/MostafaNagdy/pulls{/number}",
    "milestones_url": "https://api.github.com/repos/mostafanagedy/MostafaNagdy/milestones{/number}",
    "notifications_url": "https://api.github.com/repos/mostafanagedy/MostafaNagdy/notifications{?since,all,participating}",
    "labels_url": "https://api.github.com/repos/mostafanagedy/MostafaNagdy/labels{/name}",
    "releases_url": "https://api.github.com/repos/mostafanagedy/MostafaNagdy/releases{/id}",
    "deployments_url": "https://api.github.com/repos/mostafanagedy/MostafaNagdy/deployments",
    "created_at": "2026-01-24T15:45:52Z",
    "updated_at": "2026-02-27T14:57:58Z",
    "pushed_at": "2026-03-03T10:40:12Z",
    "git_url": "git://github.com/mostafanagedy/MostafaNagdy.git",
    "ssh_url": "git@github.com:mostafanagedy/MostafaNagdy.git",
    "clone_url": "https://github.com/mostafanagedy/MostafaNagdy.git",
    "svn_url": "https://github.com/mostafanagedy/MostafaNagdy",
    "homepage": "https://mostafa-nagdy.vercel.app",
    "size": 13,
    "stargazers_count": 4,
    "watchers_count": 4,
    "language": null,
    "has_issues": true,
    "has_projects": true,
    "has_downloads": true,
    "has_wiki": true,
    "has_pages": false,
    "has_discussions": false,
    "forks_count": 0,
    "mirror_url": null,
    "archived": false,
    "disabled": false,
    "open_issues_count": 1,
    "license": null,
    "allow_forking": true,
    "is_template": false,
    "web_commit_signoff_required": false,
    "has_pull_requests": true,
    "pull_request_creation_policy": "all",
    "topics": [

    ],
    "visibility": "public",
    "forks": 0,
    "open_issues": 1,
    "watchers": 4,
    "default_branch": "main"
  },
  {
    "id": 1176167047,
    "node_id": "R_kgDORhrihw",
    "name": "my_Certificates",
    "full_name": "mostafanagedy/my_Certificates",
    "private": false,
    "owner": {
      "login": "mostafanagedy",
      "id": 214047181,
      "node_id": "U_kgDODMIZzQ",
      "avatar_url": "https://avatars.githubusercontent.com/u/214047181?v=4",
      "gravatar_id": "",
      "url": "https://api.github.com/users/mostafanagedy",
      "html_url": "https://github.com/mostafanagedy",
      "followers_url": "https://api.github.com/users/mostafanagedy/followers",
      "following_url": "https://api.github.com/users/mostafanagedy/following{/other_user}",
      "gists_url": "https://api.github.com/users/mostafanagedy/gists{/gist_id}",
      "starred_url": "https://api.github.com/users/mostafanagedy/starred{/owner}{/repo}",
      "subscriptions_url": "https://api.github.com/users/mostafanagedy/subscriptions",
      "organizations_url": "https://api.github.com/users/mostafanagedy/orgs",
      "repos_url": "https://api.github.com/users/mostafanagedy/repos",
      "events_url": "https://api.github.com/users/mostafanagedy/events{/privacy}",
      "received_events_url": "https://api.github.com/users/mostafanagedy/received_events",
      "type": "User",
      "user_view_type": "public",
      "site_admin": false
    },
    "html_url": "https://github.com/mostafanagedy/my_Certificates",
    "description": null,
    "fork": false,
    "url": "https://api.github.com/repos/mostafanagedy/my_Certificates",
    "forks_url": "https://api.github.com/repos/mostafanagedy/my_Certificates/forks",
    "keys_url": "https://api.github.com/repos/mostafanagedy/my_Certificates/keys{/key_id}",
    "collaborators_url": "https://api.github.com/repos/mostafanagedy/my_Certificates/collaborators{/collaborator}",
    "teams_url": "https://api.github.com/repos/mostafanagedy/my_Certificates/teams",
    "hooks_url": "https://api.github.com/repos/mostafanagedy/my_Certificates/hooks",
    "issue_events_url": "https://api.github.com/repos/mostafanagedy/my_Certificates/issues/events{/number}",
    "events_url": "https://api.github.com/repos/mostafanagedy/my_Certificates/events",
    "assignees_url": "https://api.github.com/repos/mostafanagedy/my_Certificates/assignees{/user}",
    "branches_url": "https://api.github.com/repos/mostafanagedy/my_Certificates/branches{/branch}",
    "tags_url": "https://api.github.com/repos/mostafanagedy/my_Certificates/tags",
    "blobs_url": "https://api.github.com/repos/mostafanagedy/my_Certificates/git/blobs{/sha}",
    "git_tags_url": "https://api.github.com/repos/mostafanagedy/my_Certificates/git/tags{/sha}",
    "git_refs_url": "https://api.github.com/repos/mostafanagedy/my_Certificates/git/refs{/sha}",
    "trees_url": "https://api.github.com/repos/mostafanagedy/my_Certificates/git/trees{/sha}",
    "statuses_url": "https://api.github.com/repos/mostafanagedy/my_Certificates/statuses/{sha}",
    "languages_url": "https://api.github.com/repos/mostafanagedy/my_Certificates/languages",
    "stargazers_url": "https://api.github.com/repos/mostafanagedy/my_Certificates/stargazers",
    "contributors_url": "https://api.github.com/repos/mostafanagedy/my_Certificates/contributors",
    "subscribers_url": "https://api.github.com/repos/mostafanagedy/my_Certificates/subscribers",
    "subscription_url": "https://api.github.com/repos/mostafanagedy/my_Certificates/subscription",
    "commits_url": "https://api.github.com/repos/mostafanagedy/my_Certificates/commits{/sha}",
    "git_commits_url": "https://api.github.com/repos/mostafanagedy/my_Certificates/git/commits{/sha}",
    "comments_url": "https://api.github.com/repos/mostafanagedy/my_Certificates/comments{/number}",
    "issue_comment_url": "https://api.github.com/repos/mostafanagedy/my_Certificates/issues/comments{/number}",
    "contents_url": "https://api.github.com/repos/mostafanagedy/my_Certificates/contents/{+path}",
    "compare_url": "https://api.github.com/repos/mostafanagedy/my_Certificates/compare/{base}...{head}",
    "merges_url": "https://api.github.com/repos/mostafanagedy/my_Certificates/merges",
    "archive_url": "https://api.github.com/repos/mostafanagedy/my_Certificates/{archive_format}{/ref}",
    "downloads_url": "https://api.github.com/repos/mostafanagedy/my_Certificates/downloads",
    "issues_url": "https://api.github.com/repos/mostafanagedy/my_Certificates/issues{/number}",
    "pulls_url": "https://api.github.com/repos/mostafanagedy/my_Certificates/pulls{/number}",
    "milestones_url": "https://api.github.com/repos/mostafanagedy/my_Certificates/milestones{/number}",
    "notifications_url": "https://api.github.com/repos/mostafanagedy/my_Certificates/notifications{?since,all,participating}",
    "labels_url": "https://api.github.com/repos/mostafanagedy/my_Certificates/labels{/name}",
    "releases_url": "https://api.github.com/repos/mostafanagedy/my_Certificates/releases{/id}",
    "deployments_url": "https://api.github.com/repos/mostafanagedy/my_Certificates/deployments",
    "created_at": "2026-03-08T17:54:37Z",
    "updated_at": "2026-03-08T18:06:25Z",
    "pushed_at": "2026-03-08T18:06:21Z",
    "git_url": "git://github.com/mostafanagedy/my_Certificates.git",
    "ssh_url": "git@github.com:mostafanagedy/my_Certificates.git",
    "clone_url": "https://github.com/mostafanagedy/my_Certificates.git",
    "svn_url": "https://github.com/mostafanagedy/my_Certificates",
    "homepage": null,
    "size": 7234,
    "stargazers_count": 0,
    "watchers_count": 0,
    "language": null,
    "has_issues": true,
    "has_projects": true,
    "has_downloads": true,
    "has_wiki": true,
    "has_pages": false,
    "has_discussions": false,
    "forks_count": 0,
    "mirror_url": null,
    "archived": false,
    "disabled": false,
    "open_issues_count": 0,
    "license": null,
    "allow_forking": true,
    "is_template": false,
    "web_commit_signoff_required": false,
    "has_pull_requests": true,
    "pull_request_creation_policy": "all",
    "topics": [

    ],
    "visibility": "public",
    "forks": 0,
    "open_issues": 0,
    "watchers": 0,
    "default_branch": "main"
  },
  {
    "id": 1184628694,
    "node_id": "R_kgDORpv_1g",
    "name": "Nagedy_market",
    "full_name": "mostafanagedy/Nagedy_market",
    "private": false,
    "owner": {
      "login": "mostafanagedy",
      "id": 214047181,
      "node_id": "U_kgDODMIZzQ",
      "avatar_url": "https://avatars.githubusercontent.com/u/214047181?v=4",
      "gravatar_id": "",
      "url": "https://api.github.com/users/mostafanagedy",
      "html_url": "https://github.com/mostafanagedy",
      "followers_url": "https://api.github.com/users/mostafanagedy/followers",
      "following_url": "https://api.github.com/users/mostafanagedy/following{/other_user}",
      "gists_url": "https://api.github.com/users/mostafanagedy/gists{/gist_id}",
      "starred_url": "https://api.github.com/users/mostafanagedy/starred{/owner}{/repo}",
      "subscriptions_url": "https://api.github.com/users/mostafanagedy/subscriptions",
      "organizations_url": "https://api.github.com/users/mostafanagedy/orgs",
      "repos_url": "https://api.github.com/users/mostafanagedy/repos",
      "events_url": "https://api.github.com/users/mostafanagedy/events{/privacy}",
      "received_events_url": "https://api.github.com/users/mostafanagedy/received_events",
      "type": "User",
      "user_view_type": "public",
      "site_admin": false
    },
    "html_url": "https://github.com/mostafanagedy/Nagedy_market",
    "description": null,
    "fork": false,
    "url": "https://api.github.com/repos/mostafanagedy/Nagedy_market",
    "forks_url": "https://api.github.com/repos/mostafanagedy/Nagedy_market/forks",
    "keys_url": "https://api.github.com/repos/mostafanagedy/Nagedy_market/keys{/key_id}",
    "collaborators_url": "https://api.github.com/repos/mostafanagedy/Nagedy_market/collaborators{/collaborator}",
    "teams_url": "https://api.github.com/repos/mostafanagedy/Nagedy_market/teams",
    "hooks_url": "https://api.github.com/repos/mostafanagedy/Nagedy_market/hooks",
    "issue_events_url": "https://api.github.com/repos/mostafanagedy/Nagedy_market/issues/events{/number}",
    "events_url": "https://api.github.com/repos/mostafanagedy/Nagedy_market/events",
    "assignees_url": "https://api.github.com/repos/mostafanagedy/Nagedy_market/assignees{/user}",
    "branches_url": "https://api.github.com/repos/mostafanagedy/Nagedy_market/branches{/branch}",
    "tags_url": "https://api.github.com/repos/mostafanagedy/Nagedy_market/tags",
    "blobs_url": "https://api.github.com/repos/mostafanagedy/Nagedy_market/git/blobs{/sha}",
    "git_tags_url": "https://api.github.com/repos/mostafanagedy/Nagedy_market/git/tags{/sha}",
    "git_refs_url": "https://api.github.com/repos/mostafanagedy/Nagedy_market/git/refs{/sha}",
    "trees_url": "https://api.github.com/repos/mostafanagedy/Nagedy_market/git/trees{/sha}",
    "statuses_url": "https://api.github.com/repos/mostafanagedy/Nagedy_market/statuses/{sha}",
    "languages_url": "https://api.github.com/repos/mostafanagedy/Nagedy_market/languages",
    "stargazers_url": "https://api.github.com/repos/mostafanagedy/Nagedy_market/stargazers",
    "contributors_url": "https://api.github.com/repos/mostafanagedy/Nagedy_market/contributors",
    "subscribers_url": "https://api.github.com/repos/mostafanagedy/Nagedy_market/subscribers",
    "subscription_url": "https://api.github.com/repos/mostafanagedy/Nagedy_market/subscription",
    "commits_url": "https://api.github.com/repos/mostafanagedy/Nagedy_market/commits{/sha}",
    "git_commits_url": "https://api.github.com/repos/mostafanagedy/Nagedy_market/git/commits{/sha}",
    "comments_url": "https://api.github.com/repos/mostafanagedy/Nagedy_market/comments{/number}",
    "issue_comment_url": "https://api.github.com/repos/mostafanagedy/Nagedy_market/issues/comments{/number}",
    "contents_url": "https://api.github.com/repos/mostafanagedy/Nagedy_market/contents/{+path}",
    "compare_url": "https://api.github.com/repos/mostafanagedy/Nagedy_market/compare/{base}...{head}",
    "merges_url": "https://api.github.com/repos/mostafanagedy/Nagedy_market/merges",
    "archive_url": "https://api.github.com/repos/mostafanagedy/Nagedy_market/{archive_format}{/ref}",
    "downloads_url": "https://api.github.com/repos/mostafanagedy/Nagedy_market/downloads",
    "issues_url": "https://api.github.com/repos/mostafanagedy/Nagedy_market/issues{/number}",
    "pulls_url": "https://api.github.com/repos/mostafanagedy/Nagedy_market/pulls{/number}",
    "milestones_url": "https://api.github.com/repos/mostafanagedy/Nagedy_market/milestones{/number}",
    "notifications_url": "https://api.github.com/repos/mostafanagedy/Nagedy_market/notifications{?since,all,participating}",
    "labels_url": "https://api.github.com/repos/mostafanagedy/Nagedy_market/labels{/name}",
    "releases_url": "https://api.github.com/repos/mostafanagedy/Nagedy_market/releases{/id}",
    "deployments_url": "https://api.github.com/repos/mostafanagedy/Nagedy_market/deployments",
    "created_at": "2026-03-17T19:18:41Z",
    "updated_at": "2026-03-17T19:21:21Z",
    "pushed_at": "2026-03-17T19:21:13Z",
    "git_url": "git://github.com/mostafanagedy/Nagedy_market.git",
    "ssh_url": "git@github.com:mostafanagedy/Nagedy_market.git",
    "clone_url": "https://github.com/mostafanagedy/Nagedy_market.git",
    "svn_url": "https://github.com/mostafanagedy/Nagedy_market",
    "homepage": null,
    "size": 0,
    "stargazers_count": 0,
    "watchers_count": 0,
    "language": "TypeScript",
    "has_issues": true,
    "has_projects": true,
    "has_downloads": true,
    "has_wiki": true,
    "has_pages": false,
    "has_discussions": false,
    "forks_count": 0,
    "mirror_url": null,
    "archived": false,
    "disabled": false,
    "open_issues_count": 0,
    "license": null,
    "allow_forking": true,
    "is_template": false,
    "web_commit_signoff_required": false,
    "has_pull_requests": true,
    "pull_request_creation_policy": "all",
    "topics": [

    ],
    "visibility": "public",
    "forks": 0,
    "open_issues": 0,
    "watchers": 0,
    "default_branch": "main"
  },
  {
    "id": 1184623805,
    "node_id": "R_kgDORpvsvQ",
    "name": "portoflio",
    "full_name": "mostafanagedy/portoflio",
    "private": false,
    "owner": {
      "login": "mostafanagedy",
      "id": 214047181,
      "node_id": "U_kgDODMIZzQ",
      "avatar_url": "https://avatars.githubusercontent.com/u/214047181?v=4",
      "gravatar_id": "",
      "url": "https://api.github.com/users/mostafanagedy",
      "html_url": "https://github.com/mostafanagedy",
      "followers_url": "https://api.github.com/users/mostafanagedy/followers",
      "following_url": "https://api.github.com/users/mostafanagedy/following{/other_user}",
      "gists_url": "https://api.github.com/users/mostafanagedy/gists{/gist_id}",
      "starred_url": "https://api.github.com/users/mostafanagedy/starred{/owner}{/repo}",
      "subscriptions_url": "https://api.github.com/users/mostafanagedy/subscriptions",
      "organizations_url": "https://api.github.com/users/mostafanagedy/orgs",
      "repos_url": "https://api.github.com/users/mostafanagedy/repos",
      "events_url": "https://api.github.com/users/mostafanagedy/events{/privacy}",
      "received_events_url": "https://api.github.com/users/mostafanagedy/received_events",
      "type": "User",
      "user_view_type": "public",
      "site_admin": false
    },
    "html_url": "https://github.com/mostafanagedy/portoflio",
    "description": null,
    "fork": false,
    "url": "https://api.github.com/repos/mostafanagedy/portoflio",
    "forks_url": "https://api.github.com/repos/mostafanagedy/portoflio/forks",
    "keys_url": "https://api.github.com/repos/mostafanagedy/portoflio/keys{/key_id}",
    "collaborators_url": "https://api.github.com/repos/mostafanagedy/portoflio/collaborators{/collaborator}",
    "teams_url": "https://api.github.com/repos/mostafanagedy/portoflio/teams",
    "hooks_url": "https://api.github.com/repos/mostafanagedy/portoflio/hooks",
    "issue_events_url": "https://api.github.com/repos/mostafanagedy/portoflio/issues/events{/number}",
    "events_url": "https://api.github.com/repos/mostafanagedy/portoflio/events",
    "assignees_url": "https://api.github.com/repos/mostafanagedy/portoflio/assignees{/user}",
    "branches_url": "https://api.github.com/repos/mostafanagedy/portoflio/branches{/branch}",
    "tags_url": "https://api.github.com/repos/mostafanagedy/portoflio/tags",
    "blobs_url": "https://api.github.com/repos/mostafanagedy/portoflio/git/blobs{/sha}",
    "git_tags_url": "https://api.github.com/repos/mostafanagedy/portoflio/git/tags{/sha}",
    "git_refs_url": "https://api.github.com/repos/mostafanagedy/portoflio/git/refs{/sha}",
    "trees_url": "https://api.github.com/repos/mostafanagedy/portoflio/git/trees{/sha}",
    "statuses_url": "https://api.github.com/repos/mostafanagedy/portoflio/statuses/{sha}",
    "languages_url": "https://api.github.com/repos/mostafanagedy/portoflio/languages",
    "stargazers_url": "https://api.github.com/repos/mostafanagedy/portoflio/stargazers",
    "contributors_url": "https://api.github.com/repos/mostafanagedy/portoflio/contributors",
    "subscribers_url": "https://api.github.com/repos/mostafanagedy/portoflio/subscribers",
    "subscription_url": "https://api.github.com/repos/mostafanagedy/portoflio/subscription",
    "commits_url": "https://api.github.com/repos/mostafanagedy/portoflio/commits{/sha}",
    "git_commits_url": "https://api.github.com/repos/mostafanagedy/portoflio/git/commits{/sha}",
    "comments_url": "https://api.github.com/repos/mostafanagedy/portoflio/comments{/number}",
    "issue_comment_url": "https://api.github.com/repos/mostafanagedy/portoflio/issues/comments{/number}",
    "contents_url": "https://api.github.com/repos/mostafanagedy/portoflio/contents/{+path}",
    "compare_url": "https://api.github.com/repos/mostafanagedy/portoflio/compare/{base}...{head}",
    "merges_url": "https://api.github.com/repos/mostafanagedy/portoflio/merges",
    "archive_url": "https://api.github.com/repos/mostafanagedy/portoflio/{archive_format}{/ref}",
    "downloads_url": "https://api.github.com/repos/mostafanagedy/portoflio/downloads",
    "issues_url": "https://api.github.com/repos/mostafanagedy/portoflio/issues{/number}",
    "pulls_url": "https://api.github.com/repos/mostafanagedy/portoflio/pulls{/number}",
    "milestones_url": "https://api.github.com/repos/mostafanagedy/portoflio/milestones{/number}",
    "notifications_url": "https://api.github.com/repos/mostafanagedy/portoflio/notifications{?since,all,participating}",
    "labels_url": "https://api.github.com/repos/mostafanagedy/portoflio/labels{/name}",
    "releases_url": "https://api.github.com/repos/mostafanagedy/portoflio/releases{/id}",
    "deployments_url": "https://api.github.com/repos/mostafanagedy/portoflio/deployments",
    "created_at": "2026-03-17T19:12:05Z",
    "updated_at": "2026-03-17T19:16:03Z",
    "pushed_at": "2026-03-17T19:12:13Z",
    "git_url": "git://github.com/mostafanagedy/portoflio.git",
    "ssh_url": "git@github.com:mostafanagedy/portoflio.git",
    "clone_url": "https://github.com/mostafanagedy/portoflio.git",
    "svn_url": "https://github.com/mostafanagedy/portoflio",
    "homepage": "https://portoflio-lime.vercel.app",
    "size": 0,
    "stargazers_count": 0,
    "watchers_count": 0,
    "language": "TypeScript",
    "has_issues": true,
    "has_projects": true,
    "has_downloads": true,
    "has_wiki": true,
    "has_pages": false,
    "has_discussions": false,
    "forks_count": 0,
    "mirror_url": null,
    "archived": false,
    "disabled": false,
    "open_issues_count": 0,
    "license": null,
    "allow_forking": true,
    "is_template": false,
    "web_commit_signoff_required": false,
    "has_pull_requests": true,
    "pull_request_creation_policy": "all",
    "topics": [

    ],
    "visibility": "public",
    "forks": 0,
    "open_issues": 0,
    "watchers": 0,
    "default_branch": "main"
  },
  {
    "id": 1169793838,
    "node_id": "R_kgDORbmjLg",
    "name": "Quiz_time_project",
    "full_name": "mostafanagedy/Quiz_time_project",
    "private": false,
    "owner": {
      "login": "mostafanagedy",
      "id": 214047181,
      "node_id": "U_kgDODMIZzQ",
      "avatar_url": "https://avatars.githubusercontent.com/u/214047181?v=4",
      "gravatar_id": "",
      "url": "https://api.github.com/users/mostafanagedy",
      "html_url": "https://github.com/mostafanagedy",
      "followers_url": "https://api.github.com/users/mostafanagedy/followers",
      "following_url": "https://api.github.com/users/mostafanagedy/following{/other_user}",
      "gists_url": "https://api.github.com/users/mostafanagedy/gists{/gist_id}",
      "starred_url": "https://api.github.com/users/mostafanagedy/starred{/owner}{/repo}",
      "subscriptions_url": "https://api.github.com/users/mostafanagedy/subscriptions",
      "organizations_url": "https://api.github.com/users/mostafanagedy/orgs",
      "repos_url": "https://api.github.com/users/mostafanagedy/repos",
      "events_url": "https://api.github.com/users/mostafanagedy/events{/privacy}",
      "received_events_url": "https://api.github.com/users/mostafanagedy/received_events",
      "type": "User",
      "user_view_type": "public",
      "site_admin": false
    },
    "html_url": "https://github.com/mostafanagedy/Quiz_time_project",
    "description": "question app",
    "fork": false,
    "url": "https://api.github.com/repos/mostafanagedy/Quiz_time_project",
    "forks_url": "https://api.github.com/repos/mostafanagedy/Quiz_time_project/forks",
    "keys_url": "https://api.github.com/repos/mostafanagedy/Quiz_time_project/keys{/key_id}",
    "collaborators_url": "https://api.github.com/repos/mostafanagedy/Quiz_time_project/collaborators{/collaborator}",
    "teams_url": "https://api.github.com/repos/mostafanagedy/Quiz_time_project/teams",
    "hooks_url": "https://api.github.com/repos/mostafanagedy/Quiz_time_project/hooks",
    "issue_events_url": "https://api.github.com/repos/mostafanagedy/Quiz_time_project/issues/events{/number}",
    "events_url": "https://api.github.com/repos/mostafanagedy/Quiz_time_project/events",
    "assignees_url": "https://api.github.com/repos/mostafanagedy/Quiz_time_project/assignees{/user}",
    "branches_url": "https://api.github.com/repos/mostafanagedy/Quiz_time_project/branches{/branch}",
    "tags_url": "https://api.github.com/repos/mostafanagedy/Quiz_time_project/tags",
    "blobs_url": "https://api.github.com/repos/mostafanagedy/Quiz_time_project/git/blobs{/sha}",
    "git_tags_url": "https://api.github.com/repos/mostafanagedy/Quiz_time_project/git/tags{/sha}",
    "git_refs_url": "https://api.github.com/repos/mostafanagedy/Quiz_time_project/git/refs{/sha}",
    "trees_url": "https://api.github.com/repos/mostafanagedy/Quiz_time_project/git/trees{/sha}",
    "statuses_url": "https://api.github.com/repos/mostafanagedy/Quiz_time_project/statuses/{sha}",
    "languages_url": "https://api.github.com/repos/mostafanagedy/Quiz_time_project/languages",
    "stargazers_url": "https://api.github.com/repos/mostafanagedy/Quiz_time_project/stargazers",
    "contributors_url": "https://api.github.com/repos/mostafanagedy/Quiz_time_project/contributors",
    "subscribers_url": "https://api.github.com/repos/mostafanagedy/Quiz_time_project/subscribers",
    "subscription_url": "https://api.github.com/repos/mostafanagedy/Quiz_time_project/subscription",
    "commits_url": "https://api.github.com/repos/mostafanagedy/Quiz_time_project/commits{/sha}",
    "git_commits_url": "https://api.github.com/repos/mostafanagedy/Quiz_time_project/git/commits{/sha}",
    "comments_url": "https://api.github.com/repos/mostafanagedy/Quiz_time_project/comments{/number}",
    "issue_comment_url": "https://api.github.com/repos/mostafanagedy/Quiz_time_project/issues/comments{/number}",
    "contents_url": "https://api.github.com/repos/mostafanagedy/Quiz_time_project/contents/{+path}",
    "compare_url": "https://api.github.com/repos/mostafanagedy/Quiz_time_project/compare/{base}...{head}",
    "merges_url": "https://api.github.com/repos/mostafanagedy/Quiz_time_project/merges",
    "archive_url": "https://api.github.com/repos/mostafanagedy/Quiz_time_project/{archive_format}{/ref}",
    "downloads_url": "https://api.github.com/repos/mostafanagedy/Quiz_time_project/downloads",
    "issues_url": "https://api.github.com/repos/mostafanagedy/Quiz_time_project/issues{/number}",
    "pulls_url": "https://api.github.com/repos/mostafanagedy/Quiz_time_project/pulls{/number}",
    "milestones_url": "https://api.github.com/repos/mostafanagedy/Quiz_time_project/milestones{/number}",
    "notifications_url": "https://api.github.com/repos/mostafanagedy/Quiz_time_project/notifications{?since,all,participating}",
    "labels_url": "https://api.github.com/repos/mostafanagedy/Quiz_time_project/labels{/name}",
    "releases_url": "https://api.github.com/repos/mostafanagedy/Quiz_time_project/releases{/id}",
    "deployments_url": "https://api.github.com/repos/mostafanagedy/Quiz_time_project/deployments",
    "created_at": "2026-03-01T08:12:13Z",
    "updated_at": "2026-03-04T16:48:57Z",
    "pushed_at": "2026-03-04T16:48:00Z",
    "git_url": "git://github.com/mostafanagedy/Quiz_time_project.git",
    "ssh_url": "git@github.com:mostafanagedy/Quiz_time_project.git",
    "clone_url": "https://github.com/mostafanagedy/Quiz_time_project.git",
    "svn_url": "https://github.com/mostafanagedy/Quiz_time_project",
    "homepage": "https://mostafanagedy.github.io/Quiz_time_project/",
    "size": 18,
    "stargazers_count": 0,
    "watchers_count": 0,
    "language": "JavaScript",
    "has_issues": true,
    "has_projects": true,
    "has_downloads": true,
    "has_wiki": true,
    "has_pages": true,
    "has_discussions": false,
    "forks_count": 0,
    "mirror_url": null,
    "archived": false,
    "disabled": false,
    "open_issues_count": 0,
    "license": null,
    "allow_forking": true,
    "is_template": false,
    "web_commit_signoff_required": false,
    "has_pull_requests": true,
    "pull_request_creation_policy": "all",
    "topics": [

    ],
    "visibility": "public",
    "forks": 0,
    "open_issues": 0,
    "watchers": 0,
    "default_branch": "main"
  }
]
